pydantic_collab/__init__.py
pydantic_collab/_types.py
pydantic_collab/_utils.py
pydantic_collab/_viz.py
pydantic_collab/collab.py
pydantic_collab/custom_collabs.py
pydantic_collab-0.1.2.dist-info/METADATA
pydantic_collab-0.1.2.dist-info/WHEEL
pydantic_collab-0.1.2.dist-info/licenses/LICENSE
pydantic_collab-0.1.2.dist-info/RECORD
