Metadata-Version: 2.4
Name: pydantic_collab
Version: 0.1.2
Summary: Multi Agent System Framework built on top of Pydantic AI. 
Project-URL: Homepage, https://github.com/boazkatzir/pydantic-collab
License-File: LICENSE
Requires-Python: >=3.11
Requires-Dist: pydantic-ai-slim>=1.41.0
Requires-Dist: pydantic>=2.12.5
Provides-Extra: examples
Requires-Dist: logfire>=4.16.0; extra == 'examples'
Requires-Dist: opentelemetry-instrumentation-httpx>=0.60b1; extra == 'examples'
Requires-Dist: pydantic-ai>=1.36.0; extra == 'examples'
Provides-Extra: logfire
Requires-Dist: logfire>=4.16.0; extra == 'logfire'
Provides-Extra: viz
Requires-Dist: graphviz>=0.20.3; extra == 'viz'
Requires-Dist: matplotlib>=3.10.8; extra == 'viz'
Requires-Dist: networkx>=3.6.1; extra == 'viz'
